README.md
setup.cfg
setup.py
lenses_python/ACLHandler.py
lenses_python/ConnectorHandler.py
lenses_python/ConvertDateTime.py
lenses_python/KerberosTicket.py
lenses_python/Policy.py
lenses_python/ProcessorHandler.py
lenses_python/PublishHandler.py
lenses_python/QuotaHandler.py
lenses_python/ReadConfigFile.py
lenses_python/SchemasHandler.py
lenses_python/SqlHandler.py
lenses_python/TopicHandler.py
lenses_python/WebSocketHandler.py
lenses_python/constants.py
lenses_python/lenses.py
lenses_python.egg-info/PKG-INFO
lenses_python.egg-info/SOURCES.txt
lenses_python.egg-info/dependency_links.txt
lenses_python.egg-info/requires.txt
lenses_python.egg-info/top_level.txt