Metadata-Version: 2.1
Name: lenses-python
Version: 2.2
Summary: lenses python client
Home-page: https://github.com/Landoop/lenses-python
Author: Filippas Serepas
Author-email: info@landoop.com
License: Apache License 2.0
Download-URL: https://github.com/Landoop/lenses-python/archive/2.2.tar.gz
Platform: UNKNOWN
Requires-Python: >=3
